rlylutils/__init__.py
rlylutils/arm/__init__.py
rlylutils/configs/__init__.py
rlylutils/configs/cfg.py
rlylutils/data/__init__.py
rlylutils/data/data_op.py
rlylutils/data/lmdb.py
rlylutils/data/mynumpy.py
rlylutils/data/utils.py
rlylutils/decorators/__init__.py
rlylutils/decorators/decorators.py
rlylutils/files_op/__init__.py
rlylutils/files_op/excel.py
rlylutils/files_op/operate.py
rlylutils/files_op/te.py
rlylutils/files_op/utils.py
rlylutils/files_op/xml.py
rlylutils/image/__init__.py
rlylutils/image/img_op.py
rlylutils/image/utils.py
rlylutils/metaclass/__init__.py
rlylutils/metaclass/mcls.py
rlylutils/mousekey/__init__.py
rlylutils/multidimensional/TD.py
rlylutils/multidimensional/__init__.py
rlylutils/multidimensional/utils.py
rlylutils/speedup/__init__.py
rlylutils/speedup/multipro.py
rlylutils/speedup/mutipool.py
rlylutils/speedup/myasyncio.py
rlylutils/speedup/procon.py
rlylutils/utils/__init__.py
rlylutils/utils/cudatest.py
rlylutils/utils/del_jupyter_tem.py
rlylutils/utils/getinfos.py
rlylutils/utils/jaxtest.py
rlylutils/utils/linuxline.py
rlylutils/utils/mmtest.py
rlylutils/utils/numbatest.py
rlylutils/utils/openurl.py
rlylutils/utils/paddletest.py
rlylutils/utils/ros.py
rlylutils/utils/time_op.py
rlylutils/utils/winline.py
rlylutils/video/__init__.py
rlylutils/video/utils.py
rlylutils/video/videoop.py
rlylutils-0.1.23.dist-info/LICENSE
rlylutils-0.1.23.dist-info/METADATA
rlylutils-0.1.23.dist-info/WHEEL
rlylutils-0.1.23.dist-info/top_level.txt
rlylutils-0.1.23.dist-info/RECORD
